ndfem/__init__.py
ndfem/__main__.py
ndfem/cli.py
ndfem/main.py
ndfem/py.typed
ndfem-1.0.0.dist-info/licenses/LICENSE
ndfem-1.0.0.dist-info/METADATA
ndfem-1.0.0.dist-info/WHEEL
ndfem-1.0.0.dist-info/entry_points.txt
ndfem-1.0.0.dist-info/top_level.txt
ndfem-1.0.0.dist-info/RECORD
