Metadata-Version: 2.4
Name: ndfem
Version: 1.0.0
Summary: N-dimensional FEM for NumPy / PyTorch / JAX
Author-email: 34j <34j.95a2p@simplelogin.com>
License: MIT
Project-URL: Bug Tracker, https://github.com/34j/ndfem/issues
Project-URL: Changelog, https://github.com/34j/ndfem/blob/main/CHANGELOG.md
Project-URL: documentation, https://ndfem.readthedocs.io
Project-URL: repository, https://github.com/34j/ndfem
Classifier: Development Status :: 2 - Pre-Alpha
Classifier: Intended Audience :: Developers
Classifier: Natural Language :: English
Classifier: Operating System :: OS Independent
Classifier: Programming Language :: Python :: 3.9
Classifier: Programming Language :: Python :: 3.10
Classifier: Programming Language :: Python :: 3.11
Classifier: Programming Language :: Python :: 3.12
Classifier: Programming Language :: Python :: 3.13
Classifier: Topic :: Software Development :: Libraries
Requires-Python: >=3.9
License-File: LICENSE
Requires-Dist: rich>=10
Requires-Dist: typer<1,>=0.15
Dynamic: license-file
